COPYING
MANIFEST.in
README.md
requirements-dev.txt
requirements.txt
setup.py
facturae/__init__.py
facturae/extensions.py
facturae/facturae.py
facturae/facturae_parser.py
facturae/utils.py
facturae.egg-info/PKG-INFO
facturae.egg-info/SOURCES.txt
facturae.egg-info/dependency_links.txt
facturae.egg-info/requires.txt
facturae.egg-info/top_level.txt
specs/__init__.py
specs/invoice_parser_spec.py
specs/invoice_sign_spec.py