Metadata-Version: 2.4
Name: facturae
Version: 2.1.1
Summary: Facturae
Home-page: http://www.gisce.net
Author: GISCE-TI, S.L.
Author-email: devel@gisce.net
License: GPLv3
Classifier: Programming Language :: Python
Classifier: Programming Language :: Python :: 2.7
License-File: COPYING
Requires-Dist: lxml
Requires-Dist: libcomxml
Requires-Dist: signxml<=2.8.2; python_version <= "2.7.18"
Requires-Dist: signxml; python_version > "2.7.18"
Requires-Dist: crypto
Dynamic: author
Dynamic: author-email
Dynamic: classifier
Dynamic: description
Dynamic: home-page
Dynamic: license
Dynamic: license-file
Dynamic: requires-dist
Dynamic: summary
